.coafile
.gitlab-ci.yml
.travis.yml
LICENSE
README.md
requirements.setup.txt
requirements.test.txt
setup.py
test_wools_registration.py
wools/__init__.py
wools.egg-info/PKG-INFO
wools.egg-info/SOURCES.txt
wools.egg-info/dependency_links.txt
wools.egg-info/entry_points.txt
wools.egg-info/requires.txt
wools.egg-info/top_level.txt
wools/java/README.md
wools/java/__init__.py
wools/java/java_wool.py
wools/java/javagrouponder.py
wools/java/javanodewrapper.py
wools/java/javatyponder.py
wools/java/javautils.py
wools/java/wool.py
wools/java/akka/__init__.py
wools/java/akka/akka_wool.py
wools/java/akka/config/copyright.txt
wools/java/akka/config/wool_config.ini
wools/java/akka/templates/__init__.py
wools/java/akka/templates/backend_impl.jinja
wools/java/akka/templates/backend_interface.jinja
wools/java/akka/templates/class_extension.jinja
wools/java/akka/templates/class_type.jinja
wools/java/akka/templates/empty_config.jinja
wools/java/akka/templates/enum_type.jinja
wools/java/akka/templates/fub.jinja
wools/java/akka/templates/grouping.jinja
wools/java/akka/templates/pom.jinja
wools/java/akka/templates/routes.jinja
wools/java/akka/templates/union.jinja
wools/java/config/copyright.txt
wools/java/config/wool_config.ini
wools/java/jersey/__init__.py
wools/java/jersey/jersey_wool.py
wools/java/jersey/config/copyright.txt
wools/java/jersey/config/wool_config.ini
wools/java/jersey/templates/__init__.py
wools/java/jersey/templates/fub.jinja
wools/java/jersey/templates/grouping.jinja
wools/java/jersey/templates/pom.jinja
wools/java/jersey/templates/routes.jinja
wools/java/jersey/templates/union.jinja